{
  "name": "879",
  "children": [
    {
      "name": "1",
      "children": [
        {
          "name": "1",
          "children": [],
          "text": "[SUPPORT] Este sistema ha dado muy buenos resultados ambientales en diferentes pa\u00edses, logrando llegar a altos porcentajes de reciclado de envases.",
          "short_text": "[SUPPORT] Este sistema ha dado muy buenos resultados ambientales en diferentes pa\u00edses, logrando llegar a altos porcentajes de reciclado de envases."
        },
        {
          "name": "2",
          "children": [],
          "text": "[SUPPORT] En Alemania est\u00e1 instalado hace a\u00f1os y es algo que incentiva el reciclaje en el hogar ya que te pagan hasta 25 centimos por botella de pl\u00e1stico.",
          "short_text": "[SUPPORT] En Alemania est\u00e1 instalado hace a\u00f1os y es algo que incentiva el reciclaje en el hogar ya que te pagan hasta 25 centimos por botella de pl\u00e1stico."
        },
        {
          "name": "3",
          "children": [],
          "text": "[SUPPORT] Las empresas ganan reutilizando los envases, gana el medio ambiente disminuyendo el consumo de pl\u00e1stico y evitando tragedias como las inmensas acumulaciones de pl\u00e1stico en los mares.",
          "short_text": "[SUPPORT] Las empresas ganan reutilizando los envases, gana el medio ambiente disminuyendo el consumo de pl\u00e1stico y evitando tragedias como las inmensas acumulaciones de pl\u00e1stico en los mares."
        },
        {
          "name": "4",
          "children": [],
          "text": "[ATTACK] No estoy de acuerdo con los premios por civismo. Es un deber de todos como ciudadano.",
          "short_text": "[ATTACK] No estoy de acuerdo con los premios por civismo. Es un deber de todos como ciudadano."
        },
        {
          "name": "5",
          "children": [],
          "text": "[ATTACK] Este metodo implica que nadie te va a pagar por reciclar - Pagas el dinero que luego te van a devolver al comprarlo.",
          "short_text": "[ATTACK] Este metodo implica que nadie te va a pagar por reciclar - Pagas el dinero que luego te van a devolver al comprarlo."
        },
        {
          "name": "6",
          "children": [],
          "text": "[ATTACK] Si se te rompe el envase o la etiqueta te has quedado sin dinero.",
          "short_text": "[ATTACK] Si se te rompe el envase o la etiqueta te has quedado sin dinero."
        }
      ],
      "text": "Sistema de Retorno",
      "short_text": "Sistema de Retorno"
    },
    {
      "name": "2",
      "children": [
        {
          "name": "7",
          "children": [],
          "text": "[SUPPORT] Una gesti\u00f3n municipal en todo el proceso de la gesti\u00f3n de los alimentos sobrantes optimizar\u00eda su utilizaci\u00f3n y la gente sin recursos podr\u00eda alimentarse diariamente.",
          "short_text": "[SUPPORT] Una gesti\u00f3n municipal en todo el proceso de la gesti\u00f3n de los alimentos sobrantes optimizar\u00eda su utilizaci\u00f3n y la gente sin recursos podr\u00eda alimentarse diariamente."
        },
        {
          "name": "8",
          "children": [],
          "text": "[ATTACK] La intenci\u00f3n es buena pero esta propuesta se queda corta en muchos aspectos.",
          "short_text": "[ATTACK] La intenci\u00f3n es buena pero esta propuesta se queda corta en muchos aspectos."
        }
      ],
      "text": "Gesti\u00f3n Municipal de Alimentos Sobrantes",
      "short_text": "Gesti\u00f3n Municipal de Alimentos Sobrantes"
    },
    {
      "name": "3",
      "children": [
        {
          "name": "9",
          "children": [],
          "text": "[SUPPORT] Yo ser\u00eda partidario de este sistema si el envase no se deteriorara y se conservara intacto esto facilitar\u00eda que se devolviera al envasador.",
          "short_text": "[SUPPORT] Yo ser\u00eda partidario de este sistema si el envase no se deteriorara y se conservara intacto esto facilitar\u00eda que se devolviera al envasador."
        },
        {
          "name": "10",
          "children": [],
          "text": "[SUPPORT] Este tipo de propuestas deber\u00edan estar redirigidas para que todos los votos a favor sumaran m\u00e1s.",
          "short_text": "[SUPPORT] Este tipo de propuestas deber\u00edan estar redirigidas para que todos los votos a favor sumaran m\u00e1s."
        },
        {
          "name": "11",
          "children": [],
          "text": "[ATTACK] penalizar\u00eda a los fabricantes que utilizaran envases innecesarios lease envases de cartonpapel para contener por ejemplo varias latas de atun etc.",
          "short_text": "[ATTACK] penalizar\u00eda a los fabricantes que utilizaran envases innecesarios lease envases de cartonpapel para contener por ejemplo varias latas de atun etc."
        }
      ],
      "text": "Reutilizaci\u00f3n de Envases",
      "short_text": "Reutilizaci\u00f3n de Envases"
    }
  ],
  "text": "Si reciclas. Te pagamos",
  "short_text": "Si reciclas. Te pagamos"
}